pdsview/warningtimer.py
pdsview/band_widget.py
pdsview/channels_dialog.py
pdsview/histogram.py
pdsview/labelError.py
pdsview/textfinder.py
pdsview/__init__.py
pdsview/pdsview.py
pdsview/label.py
pdsview-0.5.1.dist-info/entry_points.txt
pdsview-0.5.1.dist-info/top_level.txt
pdsview-0.5.1.dist-info/METADATA
pdsview-0.5.1.dist-info/DESCRIPTION.rst
pdsview-0.5.1.dist-info/metadata.json
pdsview-0.5.1.dist-info/WHEEL
pdsview-0.5.1.dist-info/RECORD
