Metadata-Version: 2.0
Name: pdsview
Version: 0.5.1
Summary: PDS Image Viewer
Home-page: https://github.com/planetarypy/pdsview
Author: PlanetaryPy Developers
Author-email: contact@planetarypy.com
License: BSD
Keywords: pdsview
Platform: UNKNOWN
Classifier: Development Status :: 2 - Pre-Alpha
Classifier: Intended Audience :: Developers
Classifier: License :: OSI Approved :: BSD License
Classifier: Natural Language :: English
Classifier: Programming Language :: Python :: 2
Classifier: Programming Language :: Python :: 2.6
Classifier: Programming Language :: Python :: 2.7
Classifier: Programming Language :: Python :: 3
Classifier: Programming Language :: Python :: 3.3
Classifier: Programming Language :: Python :: 3.4
Classifier: Programming Language :: Python :: 3.5
Requires-Dist: ginga (==2.6.0)
Requires-Dist: planetaryimage (>=0.5.0)
Requires-Dist: matplotlib (>=1.5.1)
Requires-Dist: QtPy (>=1.2.1)
